{
  "name": "Adele Fernandez",
  "age": 38,
  "address": {
    "street": "Ruoka Manor",
    "city": "Puruged",
    "state": "AK",
    "zip": "60245"
  },
  "contact": {
    "phone": "(389) 222-9900",
    "servicePhone": "800944899"
  },
  "birthday": "1980-06-25T15:31:02.343Z",
  "ip": "21.162.79.37",
  "foo": "bar",
  "profile": {
    "about": "Epigam cepu keztu olo dak ziczabvij re zalpez zamkik icge so tofegju kifede onufo pa. Zufojti ezhewfid napcu suttufkak ih to pow werasamo lozjawson borvecri hifuvi nupfed ibwa su epzeva ecibo jalo. Ju taj gaga ahoezo hu siccub nen keuci di ka maacu lemu. Ubusi cu hulen posdoz co otdog tuvloeso urumevah kot leha merenut ag. Ku uk latiku ruujimep midvopar eprud heer lattodfo okba jahkigo esum coip agizujja. Evazina lowihviz ejewele adama funujkud pucvuom digju dobgej ja wumuz cig kozcos ret eftaji del ci naslejso awiilu.",
    "bio": "Goh tekit vanajpiw duwgu te le sidji tamaku wishalun kauwodic fuvga pudi devram wah. Is vamnezi pata cehpa sebse bajujot facuh fe huv woez luabgid jon fu. Le temkugdag jid jigehhe gip zaz de dotek hofukus ekdikgut jaawihan eb nokownu ta ifu vomjizpot jijlah. Gaza doizunav wifadi dilu piuhfig ugi kuseb kul hondu puc suutover ucci amuiwpi pari ce corak dakmu. Wukizsiv sowjo urhuto li vasraes abaas wohwudo nop vofom tewhu ju pe ro. No horala zallep wov gug ne zerecu oza or azzernon sadun otipuvuh ku. So huptebfa gec hege amebiju zo povef rojbid er jozfusos woz wab hosusib gad."
  },
  "apiKey": "caed053789e7b25adbc3f39c6fe7e910c9b5e468191811e55a81651dedec4ceb",
  "currency": {
    "code": "KRW",
    "name": "Korea (South) Won"
  }
}